src/slave.v
module axi_slave (
    input wire clk,
    input wire arst_n,

    // AXI4-Lite Write Address Channel
    input wire [31:0] S_AXI_AWADDR,
    input wire S_AXI_AWVALID,
    output reg S_AXI_AWREADY,

    // AXI4-Lite Write Data Channel
    input wire [31:0] S_AXI_WDATA,
    input wire [3:0] S_AXI_WSTRB,
    input wire S_AXI_WVALID,
    output reg S_AXI_WREADY,

    // AXI4-Lite Write Response Channel
    output reg [1:0] S_AXI_BRESP,
    output reg S_AXI_BVALID,
    input wire S_AXI_BREADY,

    // AXI4-Lite Read Address Channel
    input wire [31:0] S_AXI_ARADDR,
    input wire S_AXI_ARVALID,
    output reg S_AXI_ARREADY,

    // AXI4-Lite Read Data Channel
    output reg [31:0] S_AXI_RDATA,
    output reg [1:0] S_AXI_RRESP,
    output reg S_AXI_RVALID,
    input wire S_AXI_RREADY
);

    // Memory for storing data (256 x 32-bit locations)
    reg [31:0] memory [0:255];

    // Internal Registers
    reg [31:0] write_address_S;
    reg [31:0] read_address_S;
    reg write_in_progress_S;
    reg [31:0] debug_mem_value;

    // Memory Initialization to Avoid xxxx
    integer i;
    always @(posedge clk or negedge arst_n) begin
        if (!arst_n) begin
            for (i = 0; i < 256; i = i + 1) begin
                memory[i] <= 32'h00000000; // Default value = 0x00000000
            end
        end
    end

    always @(posedge clk or negedge arst_n) begin
        if (!arst_n) begin
            // Reset All Signals
            S_AXI_AWREADY <= 0;
            S_AXI_WREADY <= 0;
            S_AXI_BVALID <= 0;
            S_AXI_BRESP <= 2'b00;
            S_AXI_ARREADY <= 0;
            S_AXI_RVALID <= 0;
            S_AXI_RRESP <= 2'b00;
            write_in_progress_S <= 0;
            debug_mem_value <= 32'h00000000;
        end else begin
            //Write Operation
            // Capture Write Address
            if (S_AXI_AWVALID && !S_AXI_AWREADY) begin
                write_address_S <= S_AXI_AWADDR; 
                S_AXI_AWREADY <= 1;
            end
            if (S_AXI_AWREADY && S_AXI_AWVALID) begin
                S_AXI_AWREADY <= 0; // Deassert
                write_in_progress_S <= 1; // Mark Write in Progress
            end

            // Capture Write Data
            if (write_in_progress_S && S_AXI_WVALID && !S_AXI_WREADY) begin
                S_AXI_WREADY <= 1;
                memory[write_address_S] <= S_AXI_WDATA; // Write Data
            end

            if (S_AXI_WREADY && S_AXI_WVALID) begin
                S_AXI_WREADY <= 0;
                write_in_progress_S <= 0;
                S_AXI_BRESP <= 2'b00; // OKAY Response
                S_AXI_BVALID <= 1;
                
                // Update Debug Register Only When Write Happens
                debug_mem_value <= S_AXI_WDATA;
            end

            // Clear Write Response when acknowledged
            if (S_AXI_BVALID && S_AXI_BREADY) begin
                S_AXI_BVALID <= 0;
            end
            //Read Operation
            // Capture Read Address
            if (S_AXI_ARVALID && !S_AXI_ARREADY) begin
                read_address_S <= S_AXI_ARADDR; 
                S_AXI_ARREADY <= 1;
            end

            if (S_AXI_ARREADY && S_AXI_ARVALID) begin
                S_AXI_ARREADY <= 0; // Deassert after receiving address
                S_AXI_RDATA <= memory[read_address_S]; // Read from Memory
                S_AXI_RRESP <= 2'b00; // OKAY Response
                S_AXI_RVALID <= 1;
            end

            // Clear Read Response when acknowledged
            if (S_AXI_RVALID && S_AXI_RREADY) begin
                S_AXI_RVALID <= 0;
            end
        end
    end

endmodule

src/master.v
module axi_master (
    input wire clk,
    input wire arst_n,
    input wire start_write,
    input wire start_read,
    input wire [31:0] write_data,
    input wire [31:0] write_address_M,
    input wire [31:0] read_address,
    output reg [31:0] read_data,
    output reg write_done,
    output reg read_done,
    
    // AXI4-Lite Write Address Channel
    output reg [31:0] M_AXI_AWADDR,
    output reg M_AXI_AWVALID,
    input wire M_AXI_AWREADY,
    
    // AXI4-Lite Write Data Channel
    output reg [31:0] M_AXI_WDATA,
    output reg [3:0] M_AXI_WSTRB,
    output reg M_AXI_WVALID,
    input wire M_AXI_WREADY,
    
    // AXI4-Lite Write Response Channel
    input wire [1:0] M_AXI_BRESP,
    input wire M_AXI_BVALID,
    output reg M_AXI_BREADY,
    
    // AXI4-Lite Read Address Channel
    output reg [31:0] M_AXI_ARADDR,
    output reg M_AXI_ARVALID,
    input wire M_AXI_ARREADY,
    
    // AXI4-Lite Read Data Channel
    input wire [31:0] M_AXI_RDATA,
    input wire [1:0] M_AXI_RRESP,
    input wire M_AXI_RVALID,
    output reg M_AXI_RREADY
);

reg start_write_reg;

// State machine for controlling write and read operations
always @(posedge clk or negedge arst_n) begin
    if (!arst_n) begin
        // Reset all control signals
        M_AXI_AWVALID <= 0;
        M_AXI_WVALID  <= 0;
        M_AXI_BREADY  <= 0;
        M_AXI_ARVALID <= 0;
        M_AXI_RREADY  <= 0;
        write_done    <= 0;
        read_done     <= 0;
    end 
    else begin
        // WRITE PROCESS
        if (start_write) begin
            M_AXI_AWADDR  <= write_address_M;
            M_AXI_AWVALID <= 1;
            M_AXI_WDATA   <= write_data;
            M_AXI_WVALID  <= 1;
            M_AXI_WSTRB   <= 4'b1111; // Full word write
            write_done    <= 0; // Clear write_done flag
        end

        // Write address handshake
        if (M_AXI_AWREADY && M_AXI_AWVALID) 
            M_AXI_AWVALID <= 0; // Deassert when slave is ready

        // Write data handshake
        if (M_AXI_WREADY && M_AXI_WVALID) 
            M_AXI_WVALID <= 0; // Deassert when slave is ready

        // Write response handling
        if (M_AXI_BVALID) begin
            M_AXI_BREADY <= 1; // Acknowledge response
            write_done   <= 1; // Set write done flag
        end 
        else 
            M_AXI_BREADY <= 0; // Deassert once acknowledged

        // READ PROCESS
        if (start_read) begin
            M_AXI_ARADDR  <= read_address;
            M_AXI_ARVALID <= 1;
            read_done     <= 0; // Clear read_done flag
        end

        // Read address handshake
        if (M_AXI_ARREADY && M_AXI_ARVALID) 
            M_AXI_ARVALID <= 0; // Deassert when slave is ready

        // Read data handling
        if (M_AXI_RVALID) begin
            M_AXI_RREADY <= 1; // Acknowledge data
            read_data    <= M_AXI_RDATA; // Store received data
            read_done    <= 1; // Set read done flag
        end 
        else 
            M_AXI_RREADY <= 0; // Deassert once acknowledged
    end
end

endmodule

src/top.v
`include "master.v"
`include "slave.v"

module axi_lite_top (
    input wire clk,
    input wire arst_n,
    input wire start_write,
    input wire start_read,
    input wire [31:0] write_data,
    input wire [31:0] write_address_M,
    input wire [31:0] read_address,
    output wire [31:0] read_data,
    output wire write_done,
    output wire read_done
);

    // Internal signals to connect master and slave
    wire [31:0] axi_awaddr;
    wire axi_awvalid;
    wire axi_awready;

    wire [31:0] axi_wdata;
    wire [3:0] axi_wstrb;
    wire axi_wvalid;
    wire axi_wready;

    wire [1:0] axi_bresp;
    wire axi_bvalid;
    wire axi_bready;

    wire [31:0] axi_araddr;
    wire axi_arvalid;
    wire axi_arready;

    wire [31:0] axi_rdata;
    wire [1:0] axi_rresp;
    wire axi_rvalid;
    wire axi_rready;

    // Instantiate the AXI4-Lite Master
    axi_master master (
        .clk(clk),
        .arst_n(arst_n),
        .start_write(start_write),
        .start_read(start_read),
        .write_data(write_data),
        .write_address_M(write_address_M),
        .read_address(read_address),
        .read_data(read_data),
        .write_done(write_done),
        .read_done(read_done),

        // AXI4-Lite Write Address Channel
        .M_AXI_AWADDR(axi_awaddr),
        .M_AXI_AWVALID(axi_awvalid),
        .M_AXI_AWREADY(axi_awready),

        // AXI4-Lite Write Data Channel
        .M_AXI_WDATA(axi_wdata),
        .M_AXI_WSTRB(axi_wstrb),
        .M_AXI_WVALID(axi_wvalid),
        .M_AXI_WREADY(axi_wready),

        // AXI4-Lite Write Response Channel
        .M_AXI_BRESP(axi_bresp),
        .M_AXI_BVALID(axi_bvalid),
        .M_AXI_BREADY(axi_bready),

        // AXI4-Lite Read Address Channel
        .M_AXI_ARADDR(axi_araddr),
        .M_AXI_ARVALID(axi_arvalid),
        .M_AXI_ARREADY(axi_arready),

        // AXI4-Lite Read Data Channel
        .M_AXI_RDATA(axi_rdata),
        .M_AXI_RRESP(axi_rresp),
        .M_AXI_RVALID(axi_rvalid),
        .M_AXI_RREADY(axi_rready)
    );

    // Instantiate the AXI4-Lite Slave
    axi_slave slave (
        .clk(clk),
        .arst_n(arst_n),

        // AXI4-Lite Write Address Channel
        .S_AXI_AWADDR(axi_awaddr),
        .S_AXI_AWVALID(axi_awvalid),
        .S_AXI_AWREADY(axi_awready),

        // AXI4-Lite Write Data Channel
        .S_AXI_WDATA(axi_wdata),
        .S_AXI_WSTRB(axi_wstrb),
        .S_AXI_WVALID(axi_wvalid),
        .S_AXI_WREADY(axi_wready),

        // AXI4-Lite Write Response Channel
        .S_AXI_BRESP(axi_bresp),
        .S_AXI_BVALID(axi_bvalid),
        .S_AXI_BREADY(axi_bready),

        // AXI4-Lite Read Address Channel
        .S_AXI_ARADDR(axi_araddr),
        .S_AXI_ARVALID(axi_arvalid),
        .S_AXI_ARREADY(axi_arready),

        // AXI4-Lite Read Data Channel
        .S_AXI_RDATA(axi_rdata),
        .S_AXI_RRESP(axi_rresp),
        .S_AXI_RVALID(axi_rvalid),
        .S_AXI_RREADY(axi_rready)
    );

endmodule

tb/tb.v
`timescale 1ns / 1ps

module axi_lite_tb;

    reg clk;
    reg arst_n;
    reg [31:0] write_data;
    reg [31:0] write_address_M;
    reg [31:0] read_address;
    wire [31:0] read_data;
    wire write_done;
    wire read_done;

    reg write_trigger;  // Control signal to trigger write
    reg read_trigger;   // Control signal to trigger read
    reg start_write;
    reg start_read;

    // Instantiate the AXI4-Lite top module
    axi_lite_top uut (
        .clk(clk),
        .arst_n(arst_n),
        .start_write(start_write),
        .start_read(start_read),
        .write_data(write_data),
        .write_address_M(write_address_M),
        .read_address(read_address),
        .read_data(read_data),
        .write_done(write_done),
        .read_done(read_done)
    );

    // Clock generation
    always #5 clk = ~clk;

    // Generate `start_write` with respect to clk
    always @(posedge clk or negedge arst_n) begin
        if (!arst_n)
            start_write <= 0;
        else if (write_trigger)
            start_write <= 1;   // Enable for 1 clock cycle
        else
            start_write <= 0;   // Auto-disable after 1 clock
    end

    // Generate `start_read` with respect to clk
    always @(posedge clk or negedge arst_n) begin
        if (!arst_n)
            start_read <= 0;
        else if (read_trigger)
            start_read <= 1;   // Enable for 1 clock cycle
        else
            start_read <= 0;   // Auto-disable after 1 clock
    end

    // Main Test Cases
    initial begin
        // Initialize signals
        clk = 0;
        arst_n = 0;
        write_trigger = 0;
        read_trigger = 0;
        write_data = 32'h00000000;
        write_address_M = 32'h00000000;
        read_address = 32'h00000000;

        // Reset
        #10 arst_n = 1;
        $display(" System Reset Done.");

        // CASE 1: Simple Write & Read Transaction
        #10;
        $display(" [Test Case 1] Valid Write Operation");
        write_address_M = 32'h00000010;
        write_data = 32'hA5A5A5A5;
        write_trigger = 1;  // Trigger Write
        #10 write_trigger = 0;

        while (!write_done) #5;
        $display(" Write Operation Completed.");

        #10;
        $display(" [Test Case 1] Valid Read Operation");
        read_address = 32'h00000010;
        read_trigger = 1;  // Trigger Read
        #10 read_trigger = 0;

        while (!read_done) #5;
        $display(" Read Operation Completed. Read Data: %h", read_data);

        // CASE 2: Write & Read from Different Addresses
        #20;
        $display(" [Test Case 2] Writing to Different Address");
        write_address_M = 32'h00000020;
        write_data = 32'h12345678;
        write_trigger = 1;
        #10 write_trigger = 0;

        while (!write_done) #5;
        $display(" Write to Different Address Completed.");

        #10;
        $display(" [Test Case 2] Reading from New Address");
        read_address = 32'h00000020;
        read_trigger = 1;
        #10 read_trigger = 0;

        while (!read_done) #5;
        $display(" Read Operation Completed. Read Data: %h", read_data);

        // CASE 3: Unaligned Write (Invalid Address)
        #20;
        $display("[Test Case 3] Attempting Unaligned Write");
        write_address_M = 32'h00000013; // Unaligned address
        write_data = 32'hCAFEBABE;
        write_trigger = 1;
        #10 write_trigger = 0;

        while (!write_done) #5;
        $display(" Write to Unaligned Address Completed");

        // CASE 4: Read from Unmapped Address (Invalid Read)
        #20;
        $display(" [Test Case 4] Reading from Unmapped Address");
        read_address = 32'h0000FFFF; // Invalid address
        read_trigger = 1;
        #10 read_trigger = 0;

        while (!read_done) #5;
        $display(" Read from Unmapped Address Completed");

        // CASE 5: Back-to-Back Writes & Reads
        #20;
        $display(" [Test Case 5] Back-to-Back Writes");
        write_address_M = 32'h00000030;
        write_data = 32'h11223344;
        write_trigger = 1;
        #10 write_trigger = 0;

        write_address_M = 32'h00000040;
        write_data = 32'h55667788;
        write_trigger = 1;
        #10 write_trigger = 0;

        while (!write_done) #5;
        $display(" Back-to-Back Writes Completed.");

        #10;
        $display(" [Test Case 5] Back-to-Back Reads");
        read_address = 32'h00000030;
        read_trigger = 1;
        #10 read_trigger = 0;

        read_address = 32'h00000040;
        read_trigger = 1;
        #10 read_trigger = 0;

        while (!read_done) #5;
        $display(" Back-to-Back Reads Completed. Last Read Data: %h", read_data);

        // End Simulation
        #50;
        $display("All Test Cases Executed Successfully!");
        $finish;
    end

    // Waveform Generation
    initial begin
        $dumpfile("axi_lite.vcd");
        $dumpvars(0, uut);
    end

endmodule

axi_lite.vcd
$date
	Sat Mar 29 17:12:28 2025
$end
$version
	Icarus Verilog
$end
$timescale
	1ps
$end
$scope module axi_lite_tb $end
$scope module uut $end
$var wire 1 ! arst_n $end
$var wire 1 " clk $end
$var wire 32 # read_address [31:0] $end
$var wire 1 $ start_read $end
$var wire 1 % start_write $end
$var wire 32 & write_address_M [31:0] $end
$var wire 32 ' write_data [31:0] $end
$var wire 1 ( write_done $end
$var wire 1 ) read_done $end
$var wire 32 * read_data [31:0] $end
$var wire 1 + axi_wvalid $end
$var wire 4 , axi_wstrb [3:0] $end
$var wire 1 - axi_wready $end
$var wire 32 . axi_wdata [31:0] $end
$var wire 1 / axi_rvalid $end
$var wire 2 0 axi_rresp [1:0] $end
$var wire 1 1 axi_rready $end
$var wire 32 2 axi_rdata [31:0] $end
$var wire 1 3 axi_bvalid $end
$var wire 2 4 axi_bresp [1:0] $end
$var wire 1 5 axi_bready $end
$var wire 1 6 axi_awvalid $end
$var wire 1 7 axi_awready $end
$var wire 32 8 axi_awaddr [31:0] $end
$var wire 1 9 axi_arvalid $end
$var wire 1 : axi_arready $end
$var wire 32 ; axi_araddr [31:0] $end
$scope module master $end
$var wire 1 ! arst_n $end
$var wire 1 " clk $end
$var wire 32 < read_address [31:0] $end
$var wire 1 $ start_read $end
$var wire 1 % start_write $end
$var wire 32 = write_address_M [31:0] $end
$var wire 32 > write_data [31:0] $end
$var wire 1 - M_AXI_WREADY $end
$var wire 1 / M_AXI_RVALID $end
$var wire 2 ? M_AXI_RRESP [1:0] $end
$var wire 32 @ M_AXI_RDATA [31:0] $end
$var wire 1 3 M_AXI_BVALID $end
$var wire 2 A M_AXI_BRESP [1:0] $end
$var wire 1 7 M_AXI_AWREADY $end
$var wire 1 : M_AXI_ARREADY $end
$var reg 32 B M_AXI_ARADDR [31:0] $end
$var reg 1 9 M_AXI_ARVALID $end
$var reg 32 C M_AXI_AWADDR [31:0] $end
$var reg 1 6 M_AXI_AWVALID $end
$var reg 1 5 M_AXI_BREADY $end
$var reg 1 1 M_AXI_RREADY $end
$var reg 32 D M_AXI_WDATA [31:0] $end
$var reg 4 E M_AXI_WSTRB [3:0] $end
$var reg 1 + M_AXI_WVALID $end
$var reg 32 F read_data [31:0] $end
$var reg 1 ) read_done $end
$var reg 1 ( write_done $end
$upscope $end
$scope module slave $end
$var wire 32 G S_AXI_ARADDR [31:0] $end
$var wire 1 9 S_AXI_ARVALID $end
$var wire 32 H S_AXI_AWADDR [31:0] $end
$var wire 1 6 S_AXI_AWVALID $end
$var wire 1 5 S_AXI_BREADY $end
$var wire 1 1 S_AXI_RREADY $end
$var wire 32 I S_AXI_WDATA [31:0] $end
$var wire 4 J S_AXI_WSTRB [3:0] $end
$var wire 1 + S_AXI_WVALID $end
$var wire 1 ! arst_n $end
$var wire 1 " clk $end
$var reg 1 : S_AXI_ARREADY $end
$var reg 1 7 S_AXI_AWREADY $end
$var reg 2 K S_AXI_BRESP [1:0] $end
$var reg 1 3 S_AXI_BVALID $end
$var reg 32 L S_AXI_RDATA [31:0] $end
$var reg 2 M S_AXI_RRESP [1:0] $end
$var reg 1 / S_AXI_RVALID $end
$var reg 1 - S_AXI_WREADY $end
$var reg 32 N debug_mem_value [31:0] $end
$var reg 32 O read_address_S [31:0] $end
$var reg 32 P write_address_S [31:0] $end
$var reg 1 Q write_in_progress_S $end
$var integer 32 R i [31:0] $end
$upscope $end
$upscope $end
$upscope $end
$enddefinitions $end
$comment Show the parameter values. $end
$dumpall
$end
#0
$dumpvars
b100000000 R
0Q
bx P
bx O
b0 N
b0 M
bx L
b0 K
bx J
bx I
bx H
bx G
bx F
bx E
bx D
bx C
bx B
b0 A
bx @
b0 ?
b0 >
b0 =
b0 <
bx ;
0:
09
bx 8
07
06
05
b0 4
03
bx 2
01
b0 0
0/
bx .
0-
bx ,
0+
bx *
0)
0(
b0 '
b0 &
0%
0$
b0 #
0"
0!
$end
#5000
b100000000 R
1"
#10000
0"
1!
#15000
1"
#20000
0"
b10100101101001011010010110100101 '
b10100101101001011010010110100101 >
b10000 &
b10000 =
#25000
1%
1"
#30000
0"
#35000
b1111 ,
b1111 E
b1111 J
1+
b10100101101001011010010110100101 .
b10100101101001011010010110100101 D
b10100101101001011010010110100101 I
16
b10000 8
b10000 C
b10000 H
0%
1"
#40000
0"
#45000
17
b10000 P
1"
#50000
0"
#55000
06
1Q
07
1"
#60000
0"
#65000
1-
1"
#70000
0"
#75000
0+
b10100101101001011010010110100101 N
13
0Q
0-
1"
#80000
0"
#85000
1(
15
1"
#90000
0"
#95000
03
1"
#100000
0"
b10000 #
b10000 <
#105000
1$
05
1"
#110000
0"
#115000
19
b10000 ;
b10000 B
b10000 G
0$
1"
#120000
0"
#125000
1:
b10000 O
1"
#130000
0"
#135000
09
1/
b10100101101001011010010110100101 2
b10100101101001011010010110100101 @
b10100101101001011010010110100101 L
0:
1"
#140000
0"
#145000
1)
b10100101101001011010010110100101 *
b10100101101001011010010110100101 F
11
1"
#150000
0"
#155000
0/
1"
#160000
0"
#165000
01
1"
#170000
0"
b10010001101000101011001111000 '
b10010001101000101011001111000 >
b100000 &
b100000 =
#175000
1%
1"
#180000
0"
#185000
0%
0(
1+
b10010001101000101011001111000 .
b10010001101000101011001111000 D
b10010001101000101011001111000 I
16
b100000 8
b100000 C
b100000 H
1"
#190000
0"
b100000 #
b100000 <
#195000
17
b100000 P
1$
1"
#200000
0"
#205000
0$
1Q
07
0)
19
b100000 ;
b100000 B
b100000 G
06
1"
#210000
0"
#215000
1:
b100000 O
1-
1"
#220000
0"
b11001010111111101011101010111110 '
b11001010111111101011101010111110 >
b10011 &
b10011 =
#225000
1%
1/
b10010001101000101011001111000 2
b10010001101000101011001111000 @
b10010001101000101011001111000 L
0:
b10010001101000101011001111000 N
13
0Q
0-
09
0+
1"
#230000
0"
#235000
1)
b10010001101000101011001111000 *
b10010001101000101011001111000 F
11
1(
15
1+
b11001010111111101011101010111110 .
b11001010111111101011101010111110 D
b11001010111111101011101010111110 I
16
b10011 8
b10011 C
b10011 H
0%
1"
#240000
0"
#245000
0/
03
17
b10011 P
1"
#250000
0"
#255000
01
05
06
1Q
07
1"
#260000
0"
b1111111111111111 #
b1111111111111111 <
#265000
1$
1-
1"
#270000
0"
#275000
0)
19
b1111111111111111 ;
b1111111111111111 B
b1111111111111111 G
0+
b11001010111111101011101010111110 N
13
0Q
0-
0$
1"
#280000
0"
#285000
1:
b1111111111111111 O
15
1"
#290000
0"
b10001001000100011001101000100 '
b10001001000100011001101000100 >
b110000 &
b110000 =
#295000
09
1/
bx 2
bx @
bx L
0:
03
1%
1"
#300000
0"
b1010101011001100111011110001000 '
b1010101011001100111011110001000 >
b1000000 &
b1000000 =
#305000
1)
bx *
bx F
11
05
0(
1+
b1010101011001100111011110001000 .
b1010101011001100111011110001000 D
b1010101011001100111011110001000 I
16
b1000000 8
b1000000 C
b1000000 H
1"
#310000
0"
#315000
0/
17
b1000000 P
0%
1"
#320000
0"
#325000
1Q
07
01
06
1"
#330000
0"
#335000
1-
1"
#340000
0"
#345000
b1010101011001100111011110001000 N
13
0Q
0-
0+
1"
#350000
0"
#355000
1(
15
1"
#360000
0"
#365000
03
1"
#370000
0"
b110000 #
b110000 <
#375000
05
1$
1"
#380000
0"
b1000000 #
b1000000 <
#385000
0)
19
b1000000 ;
b1000000 B
b1000000 G
1"
#390000
0"
#395000
1:
b1000000 O
0$
1"
#400000
0"
#405000
1/
b1010101011001100111011110001000 2
b1010101011001100111011110001000 @
b1010101011001100111011110001000 L
0:
09
1"
#410000
0"
#415000
1)
b1010101011001100111011110001000 *
b1010101011001100111011110001000 F
11
1"
#420000
0"
#425000
0/
1"
#430000
0"
#435000
01
1"
